config2hash/__init__.py
config2hash/hash_generator.py
config2hash-0.0.2.dist-info/LICENSE
config2hash-0.0.2.dist-info/METADATA
config2hash-0.0.2.dist-info/WHEEL
config2hash-0.0.2.dist-info/top_level.txt
config2hash-0.0.2.dist-info/RECORD
