Metadata-Version: 2.1
Name: config2hash
Version: 0.0.2
Summary: UNKNOWN
Home-page: https://github.com/nabenabe0928/config2hash
Author: nabenabe0928
Author-email: shuhei.watanabe.utokyo@gmail.com
License: UNKNOWN
Platform: Linux
Requires-Python: >=3.8
Requires-Dist: numpy
